{"version":"0.0.0","name":"vite-vue3-ts-demo","dependencies":{"ansi-regex":{"version":"2.1.1"},"asynckit":{"version":"0.4.0"},"bcrypt-pbkdf":{"version":"1.0.2"},"dashdash":{"version":"1.14.1"},"ecc-jsbn":{"version":"0.1.2"},"util-deprecate":{"version":"1.0.2"},"validate-npm-package-license":{"version":"3.0.4"},"verror":{"version":"1.10.0"},"void-elements":{"version":"3.1.0"},"vscode-languageserver-textdocument":{"version":"1.0.2"},"vscode-languageserver-types":{"version":"3.17.0-next.4"},"vscode-nls":{"version":"5.0.0"},"vscode-pug-languageservice":{"version":"0.27.24"},"vscode-uri":{"version":"3.0.2"},"vue-router":{"version":"4.0.12"},"vue":{"version":"3.2.20"},"vuex":{"version":"4.0.2"},"which-module":{"version":"2.0.0"},"which":{"version":"2.0.2"},"with":{"version":"7.0.2"},"wrap-ansi":{"version":"5.1.0"},"wrappy":{"version":"1.0.2"},"y18n":{"version":"4.0.3"},"yargs-parser":{"version":"20.2.9"}}}